README.md
setup.py
bin/__init__.py
bin/set-todoBot
bin/todoBot
docs/__init__.py
tests/__init__.py
todoBot/__init__.py
todoBot/apihelper.py
todoBot/botPatch.py
todoBot/bot_types.py
todoBot/bot_variables.py
todoBot/database.py
todoBot/telebot.py
todoBot/telegrambot.py
todoBot/timeManip.py
todoBot/types.py
todoBot/util.py
todoBot.egg-info/PKG-INFO
todoBot.egg-info/SOURCES.txt
todoBot.egg-info/dependency_links.txt
todoBot.egg-info/requires.txt
todoBot.egg-info/top_level.txt