Metadata-Version: 1.1
Name: todoBot
Version: 0.2
Summary: Simple bot
Home-page: https://github.com/lrusifikator/todoBot
Author: Ruslan Yakushev
Author-email: yakushev.rusl101@gmail.com
License: MIT
Project-URL: Source Code, https://github.com/lrusifikator/todoBot
Project-URL: Documentation, https://github.com/lrusifikator/todoBot/docs
Platform: UNKNOWN
Classifier: Programming Language :: Python :: 3
Classifier: License :: OSI Approved :: MIT License
Classifier: Operating System :: OS Independent
